{"items": [{"admin1Code": 901013, "admin1Name": "Administrative unit not available", "admin2Code": 1011057, "admin2Name": "Administrative unit not available", "marketId": 2797, "marketLatitude": 1.440555556, "marketLocalName": null, "marketLongitude": 30.477134, "marketName": "Kasenyi"}, {"admin1Code": 901011, "admin1Name": "Administrative unit not available", "admin2Code": 1011055, "admin2Name": "Administrative unit not available", "marketId": 147, "marketLatitude": -3.406667, "marketLocalName": null, "marketLongitude": 29.145833, "marketName": "Uvira"}, {"admin1Code": 900155, "admin1Name": "Bas-Uele", "admin2Code": 1002924, "admin2Name": "Bondo", "marketId": 1648, "marketLatitude": 3.971459, "marketLocalName": null, "marketLongitude": 23.3978499999999, "marketName": "Zongo"}, {"admin1Code": 900150, "admin1Name": "Equateur", "admin2Code": 1002898, "admin2Name": "Bomongo", "marketId": 146, "marketLatitude": 0.066667, "marketLocalName": null, "marketLongitude": 18.266667, "marketName": "Mbandaka"}, {"admin1Code": 900162, "admin1Name": "Haut-Katanga", "admin2Code": 1003016, "admin2Name": "Likasi", "marketId": 1606, "marketLatitude": -10.9813889, "marketLocalName": null, "marketLongitude": 26.7333333, "marketName": "Likasi"}, {"admin1Code": 900162, "admin1Name": "Haut-Katanga", "admin2Code": 1003017, "admin2Name": "Lubumbashi", "marketId": 145, "marketLatitude": -11.666667, "marketLocalName": null, "marketLongitude": 27.466667, "marketName": "Lubumbashi"}, {"admin1Code": 900162, "admin1Name": "Haut-Katanga", "admin2Code": 1003017, "admin2Name": "Lubumbashi", "marketId": 4141, "marketLatitude": -11.64685667, "marketLocalName": null, "marketLongitude": 27.544885, "marketName": "Luowoshi"}, {"admin1Code": 900162, "admin1Name": "Haut-Katanga", "admin2Code": 1002965, "admin2Name": "Mitwaba", "marketId": 4521, "marketLatitude": -8.890555, "marketLocalName": null, "marketLongitude": 26.873528, "marketName": "Katanga Kivu"}, {"admin1Code": 900162, "admin1Name": "Haut-Katanga", "admin2Code": 1002966, "admin2Name": "Pweto", "marketId": 2272, "marketLatitude": -8.46845531463623, "marketLocalName": null, "marketLongitude": 28.89792251586914, "marketName": "Pweto"}, {"admin1Code": 900160, "admin1Name": "Haut-Lomami", "admin2Code": 1003079, "admin2Name": "Kamina city", "marketId": 1604, "marketLatitude": -8.7386111, "marketLocalName": null, "marketLongitude": 24.9905556, "marketName": "Kamina"}, {"admin1Code": 900156, "admin1Name": "Haut-Uele", "admin2Code": 1003060, "admin2Name": "Aba", "marketId": 2271, "marketLatitude": 3.865166664123535, "marketLocalName": null, "marketLongitude": 30.234527587890625, "marketName": "Aba"}, {"admin1Code": 900156, "admin1Name": "Haut-Uele", "admin2Code": 1003060, "admin2Name": "Aba", "marketId": 2270, "marketLatitude": 3.8481333255767822, "marketLocalName": null, "marketLongitude": 30.2016658782959, "marketName": "Meri"}, {"admin1Code": 900156, "admin1Name": "Haut-Uele", "admin2Code": 1002930, "admin2Name": "Dungu", "marketId": 2269, "marketLatitude": 4.71750020980835, "marketLocalName": null, "marketLongitude": 27.680967330932617, "marketName": "Doruma"}, {"admin1Code": 900156, "admin1Name": "Haut-Uele", "admin2Code": 1002931, "admin2Name": "Faradje", "marketId": 2798, "marketLatitude": 3.59464, "marketLocalName": null, "marketLongitude": 30.17245, "marketName": "Bele"}, {"admin1Code": 900156, "admin1Name": "Haut-Uele", "admin2Code": 1003058, "admin2Name": "Isiro", "marketId": 1609, "marketLatitude": 2.7666667, "marketLocalName": null, "marketLongitude": 27.6166667, "marketName": "Isiro"}, {"admin1Code": 900145, "admin1Name": "Ituri", "admin2Code": 1002937, "admin2Name": "Aru", "marketId": 2273, "marketLatitude": 2.799888849258423, "marketLocalName": null, "marketLongitude": 30.337785720825195, "marketName": "Biringi"}, {"admin1Code": 900145, "admin1Name": "Ituri", "admin2Code": 1003069, "admin2Name": "Aru city", "marketId": 2274, "marketLatitude": 2.8594443798065186, "marketLocalName": null, "marketLongitude": 30.824167251586914, "marketName": "Aru"}, {"admin1Code": 900145, "admin1Name": "Ituri", "admin2Code": 1003063, "admin2Name": "Bunia", "marketId": 151, "marketLatitude": 1.566667, "marketLocalName": null, "marketLongitude": 30.25, "marketName": "Bunia"}, {"admin1Code": 900145, "admin1Name": "Ituri", "admin2Code": 1002865, "admin2Name": "Djugu", "marketId": 2791, "marketLatitude": 1.5452, "marketLocalName": null, "marketLongitude": 30.3028, "marketName": "Bule"}, {"admin1Code": 900145, "admin1Name": "Ituri", "admin2Code": 1002865, "admin2Name": "Djugu", "marketId": 4152, "marketLatitude": 1.735375, "marketLocalName": null, "marketLongitude": 30.30366833, "marketName": "Iga"}, {"admin1Code": 900145, "admin1Name": "Ituri", "admin2Code": 1002865, "admin2Name": "Djugu", "marketId": 2792, "marketLatitude": 1.4439, "marketLocalName": null, "marketLongitude": 30.3256, "marketName": "Largu"}, {"admin1Code": 900145, "admin1Name": "Ituri", "admin2Code": 1002865, "admin2Name": "Djugu", "marketId": 2794, "marketLatitude": 1.98, "marketLocalName": null, "marketLongitude": 30.5848, "marketName": "Mahagi"}, {"admin1Code": 900145, "admin1Name": "Ituri", "admin2Code": 1002934, "admin2Name": "Irumu", "marketId": 2796, "marketLatitude": 1.392222222, "marketLocalName": null, "marketLongitude": 30.44222222, "marketName": "Tchomia"}, {"admin1Code": 900145, "admin1Name": "Ituri", "admin2Code": 1002936, "admin2Name": "Mahagi", "marketId": 4524, "marketLatitude": 2.0444444, "marketLocalName": null, "marketLongitude": 31.0555, "marketName": "Ramogi"}, {"admin1Code": 900145, "admin1Name": "Ituri", "admin2Code": 1002935, "admin2Name": "Mambasa", "marketId": 2795, "marketLatitude": 1.2153, "marketLocalName": null, "marketLongitude": 29.454, "marketName": "Komanda"}, {"admin1Code": 900145, "admin1Name": "Ituri", "admin2Code": 1002935, "admin2Name": "Mambasa", "marketId": 2793, "marketLatitude": 1.2153, "marketLocalName": null, "marketLongitude": 29.454, "marketName": "Mambasa"}, {"admin1Code": 900166, "admin1Name": "Kasai", "admin2Code": 1002990, "admin2Name": "Ilebo", "marketId": 2315, "marketLatitude": -5.461389064788818, "marketLocalName": null, "marketLongitude": 20.466388702392578, "marketName": "Banga Lubaka"}, {"admin1Code": 900166, "admin1Name": "Kasai", "admin2Code": 1002990, "admin2Name": "Ilebo", "marketId": 2414, "marketLatitude": -5.782777777777778, "marketLocalName": null, "marketLongitude": 20.741111111111113, "marketName": "Bipongo"}, {"admin1Code": 900166, "admin1Name": "Kasai", "admin2Code": 1002990, "admin2Name": "Ilebo", "marketId": 2418, "marketLatitude": -5.571666666666666, "marketLocalName": null, "marketLongitude": 20.845555555555553, "marketName": "Mayimbi"}, {"admin1Code": 900166, "admin1Name": "Kasai", "admin2Code": 1002989, "admin2Name": "Kamonia", "marketId": 2417, "marketLatitude": -7.238611111111111, "marketLocalName": null, "marketLongitude": 20.88722222222222, "marketName": "Kamako"}, {"admin1Code": 900166, "admin1Name": "Kasai", "admin2Code": 1002989, "admin2Name": "Kamonia", "marketId": 2267, "marketLatitude": -6.456669807434082, "marketLocalName": null, "marketLongitude": 20.79277992248535, "marketName": "Kamalenga"}, {"admin1Code": 900166, "admin1Name": "Kasai", "admin2Code": 1002989, "admin2Name": "Kamonia", "marketId": 3215, "marketLatitude": -6.881351, "marketLocalName": null, "marketLongitude": 20.923498, "marketName": "Kamonia"}, {"admin1Code": 900166, "admin1Name": "Kasai", "admin2Code": 1002989, "admin2Name": "Kamonia", "marketId": 2266, "marketLatitude": -6.217219829559326, "marketLocalName": null, "marketLongitude": 21.415369033813477, "marketName": "Kamwesha"}, {"admin1Code": 900166, "admin1Name": "Kasai", "admin2Code": 1002989, "admin2Name": "Kamonia", "marketId": 2420, "marketLatitude": -6.456666666666667, "marketLocalName": null, "marketLongitude": 20.79277777777778, "marketName": "Mutena"}, {"admin1Code": 900166, "admin1Name": "Kasai", "admin2Code": 1002988, "admin2Name": "Luebo", "marketId": 3040, "marketLatitude": -5.445277778, "marketLocalName": null, "marketLongitude": 20.99833333, "marketName": "Ndjoko Punda"}, {"admin1Code": 900166, "admin1Name": "Kasai", "admin2Code": 1003093, "admin2Name": "Luebo city", "marketId": 3216, "marketLatitude": -5.349504, "marketLocalName": null, "marketLongitude": 21.423468, "marketName": "Luebo"}, {"admin1Code": 900166, "admin1Name": "Kasai", "admin2Code": 1003092, "admin2Name": "Tshikapa", "marketId": 2265, "marketLatitude": -6.414720058441162, "marketLocalName": null, "marketLongitude": 20.79277992248535, "marketName": "Dibumba"}, {"admin1Code": 900166, "admin1Name": "Kasai", "admin2Code": 1003092, "admin2Name": "Tshikapa", "marketId": 1601, "marketLatitude": -6.4166667, "marketLocalName": null, "marketLongitude": 20.8, "marketName": "Tshikapa"}, {"admin1Code": 900166, "admin1Name": "Kasai", "admin2Code": 1003092, "admin2Name": "Tshikapa", "marketId": 2264, "marketLatitude": -6.414999961853027, "marketLocalName": null, "marketLongitude": 20.797500610351562, "marketName": "Zkele"}, {"admin1Code": 900165, "admin1Name": "Kasai-Central", "admin2Code": 1002986, "admin2Name": "Demba", "marketId": 4150, "marketLatitude": -5.49608, "marketLocalName": null, "marketLongitude": 22.271005, "marketName": "Central de Demba"}, {"admin1Code": 900165, "admin1Name": "Kasai-Central", "admin2Code": 1002986, "admin2Name": "Demba", "marketId": 4151, "marketLatitude": -5.706761667, "marketLocalName": null, "marketLongitude": 22.3303, "marketName": "Zapo Zapo"}, {"admin1Code": 900165, "admin1Name": "Kasai-Central", "admin2Code": 1002983, "admin2Name": "Dibaya", "marketId": 3217, "marketLatitude": -6.306804, "marketLocalName": null, "marketLongitude": 22.521998, "marketName": "Bunkonde Centre"}, {"admin1Code": 900165, "admin1Name": "Kasai-Central", "admin2Code": 1002987, "admin2Name": "Dimbelenge", "marketId": 2277, "marketLatitude": -5.69444465637207, "marketLocalName": null, "marketLongitude": 22.994443893432617, "marketName": "Kajiba"}, {"admin1Code": 900165, "admin1Name": "Kasai-Central", "admin2Code": 1002987, "admin2Name": "Dimbelenge", "marketId": 2278, "marketLatitude": -5.019444465637207, "marketLocalName": null, "marketLongitude": 22.88888931274414, "marketName": "Kalombo"}, {"admin1Code": 900165, "admin1Name": "Kasai-Central", "admin2Code": 1002987, "admin2Name": "Dimbelenge", "marketId": 3041, "marketLatitude": -4.915833333, "marketLocalName": null, "marketLongitude": 22.59416667, "marketName": "Kasongo Mule"}, {"admin1Code": 900165, "admin1Name": "Kasai-Central", "admin2Code": 1002987, "admin2Name": "Dimbelenge", "marketId": 2276, "marketLatitude": -5.141666889190674, "marketLocalName": null, "marketLongitude": 22.905555725097656, "marketName": "Mashala"}, {"admin1Code": 900165, "admin1Name": "Kasai-Central", "admin2Code": 1002987, "admin2Name": "Dimbelenge", "marketId": 2275, "marketLatitude": -4.72778, "marketLocalName": null, "marketLongitude": 22.63989, "marketName": "Mwetshi"}, {"admin1Code": 900165, "admin1Name": "Kasai-Central", "admin2Code": 1002987, "admin2Name": "Dimbelenge", "marketId": 2314, "marketLatitude": -4.9083333015441895, "marketLocalName": null, "marketLongitude": 22.50611114501953, "marketName": "Tshibamba"}, {"admin1Code": 900165, "admin1Name": "Kasai-Central", "admin2Code": 1003012, "admin2Name": "Kananga", "marketId": 1602, "marketLatitude": -5.8958333, "marketLocalName": null, "marketLongitude": 22.4177778, "marketName": "Kananga"}, {"admin1Code": 900165, "admin1Name": "Kasai-Central", "admin2Code": 1002985, "admin2Name": "Kazumba", "marketId": 3218, "marketLatitude": -6.1824770000000004, "marketLocalName": null, "marketLongitude": 22.418833, "marketName": "Tshikele"}, {"admin1Code": 900165, "admin1Name": "Kasai-Central", "admin2Code": 1002984, "admin2Name": "Luiza", "marketId": 3219, "marketLatitude": -7.201406, "marketLocalName": null, "marketLongitude": 22.395072, "marketName": "Luiza Centre"}, {"admin1Code": 900165, "admin1Name": "Kasai-Central", "admin2Code": 1002984, "admin2Name": "Luiza", "marketId": 4615, "marketLatitude": -7.552072, "marketLocalName": null, "marketLongitude": 22.545326, "marketName": "Masuika"}, {"admin1Code": 900165, "admin1Name": "Kasai-Central", "admin2Code": 1003091, "admin2Name": "Tshimbulu", "marketId": 4523, "marketLatitude": -6.474206, "marketLocalName": null, "marketLongitude": 22.866196, "marketName": "Tshimbulu"}, {"admin1Code": 900143, "admin1Name": "Kasai-Oriental", "admin2Code": 1002969, "admin2Name": "Kabeya-Kamwanga", "marketId": 4148, "marketLatitude": -6.26569, "marketLocalName": null, "marketLongitude": 23.1065616, "marketName": "Tshitshianku"}, {"admin1Code": 900143, "admin1Name": "Kasai-Oriental", "admin2Code": 1003013, "admin2Name": "Mbuji-Mayi", "marketId": 1651, "marketLatitude": -6.15, "marketLocalName": null, "marketLongitude": 23.6, "marketName": "Mbuji-mayi"}, {"admin1Code": 900143, "admin1Name": "Kasai-Oriental", "admin2Code": 1002863, "admin2Name": "Tshilenge", "marketId": 4146, "marketLatitude": -6.186825596, "marketLocalName": null, "marketLongitude": 23.65436762, "marketName": "Luamuela"}, {"admin1Code": 900143, "admin1Name": "Kasai-Oriental", "admin2Code": 1003086, "admin2Name": "Tshilenge city", "marketId": 4147, "marketLatitude": -6.235131907, "marketLocalName": null, "marketLongitude": 23.75572298, "marketName": "Tshilenge"}, {"admin1Code": 900168, "admin1Name": "Kinshasa", "admin2Code": 1003005, "admin2Name": "Kinshasa", "marketId": 3984, "marketLatitude": -4.46637614, "marketLocalName": null, "marketLongitude": 15.46070082, "marketName": "Buma"}, {"admin1Code": 900168, "admin1Name": "Kinshasa", "admin2Code": 1003005, "admin2Name": "Kinshasa", "marketId": 3985, "marketLatitude": -4.21756627, "marketLocalName": null, "marketLongitude": 15.57735316, "marketName": "Domaine"}, {"admin1Code": 900168, "admin1Name": "Kinshasa", "admin2Code": 1003005, "admin2Name": "Kinshasa", "marketId": 3982, "marketLatitude": -4.32198455, "marketLocalName": "Kinkole P\u00eacheurs", "marketLongitude": 15.51229137, "marketName": "Kinkole Pecheurs"}, {"admin1Code": 900168, "admin1Name": "Kinshasa", "admin2Code": 1003005, "admin2Name": "Kinshasa", "marketId": 144, "marketLatitude": -4.3, "marketLocalName": null, "marketLongitude": 15.3, "marketName": "Kinshasa"}, {"admin1Code": 900168, "admin1Name": "Kinshasa", "admin2Code": 1003005, "admin2Name": "Kinshasa", "marketId": 4110, "marketLatitude": -4.40329, "marketLocalName": null, "marketLongitude": 15.37774167, "marketName": "Liberte"}, {"admin1Code": 900168, "admin1Name": "Kinshasa", "admin2Code": 1003005, "admin2Name": "Kinshasa", "marketId": 3986, "marketLatitude": -4.42059385, "marketLocalName": null, "marketLongitude": 15.45648056, "marketName": "Mbila"}, {"admin1Code": 900168, "admin1Name": "Kinshasa", "admin2Code": 1003005, "admin2Name": "Kinshasa", "marketId": 3987, "marketLatitude": -4.31685643, "marketLocalName": null, "marketLongitude": 15.51125509, "marketName": "Port Kinkole"}, {"admin1Code": 900168, "admin1Name": "Kinshasa", "admin2Code": 1003005, "admin2Name": "Kinshasa", "marketId": 4111, "marketLatitude": -4.40599, "marketLocalName": null, "marketLongitude": 15.256435, "marketName": "UPN"}, {"admin1Code": 900146, "admin1Name": "Kongo-Central", "admin2Code": 1003006, "admin2Name": "Boma", "marketId": 1598, "marketLatitude": -5.82, "marketLocalName": null, "marketLongitude": 13.05, "marketName": "Boma"}, {"admin1Code": 900146, "admin1Name": "Kongo-Central", "admin2Code": 1003008, "admin2Name": "Matadi", "marketId": 1599, "marketLatitude": -5.8166667, "marketLocalName": null, "marketLongitude": 13.45, "marketName": "Matadi"}, {"admin1Code": 900146, "admin1Name": "Kongo-Central", "admin2Code": 1002868, "admin2Name": "Mbanza-Ngungu", "marketId": 4121, "marketLatitude": -5.49999, "marketLocalName": null, "marketLongitude": 14.68457333, "marketName": "Kwilu Ngongo"}, {"admin1Code": 900146, "admin1Name": "Kongo-Central", "admin2Code": 1003032, "admin2Name": "Mbanza-Ngungu city", "marketId": 4122, "marketLatitude": -5.25799, "marketLocalName": null, "marketLongitude": 14.85997667, "marketName": "Mbanza-Ngungu"}, {"admin1Code": 900146, "admin1Name": "Kongo-Central", "admin2Code": 1002867, "admin2Name": "Seke-Banza", "marketId": 4118, "marketLatitude": -5.49892, "marketLocalName": null, "marketLongitude": 13.28622, "marketName": "Kinzau-Mvuete"}, {"admin1Code": 900146, "admin1Name": "Kongo-Central", "admin2Code": 1002867, "admin2Name": "Seke-Banza", "marketId": 4119, "marketLatitude": -5.608295, "marketLocalName": null, "marketLongitude": 13.44628, "marketName": "Sanda"}, {"admin1Code": 900146, "admin1Name": "Kongo-Central", "admin2Code": 1002869, "admin2Name": "Songololo", "marketId": 4120, "marketLatitude": -5.69789931, "marketLocalName": null, "marketLongitude": 14.0387468, "marketName": "Songololo"}, {"admin1Code": 900149, "admin1Name": "Kwango", "admin2Code": 1002884, "admin2Name": "Feshi", "marketId": 2419, "marketLatitude": -6.25, "marketLocalName": null, "marketLongitude": 19.160277777777775, "marketName": "Mukoso"}, {"admin1Code": 900149, "admin1Name": "Kwango", "admin2Code": 1002885, "admin2Name": "Kahemba", "marketId": 2415, "marketLatitude": -7.291111111111111, "marketLocalName": null, "marketLongitude": 18.96, "marketName": "Kahemba"}, {"admin1Code": 900149, "admin1Name": "Kwango", "admin2Code": 1002885, "admin2Name": "Kahemba", "marketId": 2416, "marketLatitude": -7.64861111111111, "marketLocalName": null, "marketLongitude": 18.490277777777777, "marketName": "Kajiji"}, {"admin1Code": 900148, "admin1Name": "Kwilu", "admin2Code": 1003010, "admin2Name": "Bandundu", "marketId": 1596, "marketLatitude": -3.31, "marketLocalName": null, "marketLongitude": 17.37, "marketName": "Bandundu ville"}, {"admin1Code": 900148, "admin1Name": "Kwilu", "admin2Code": 1003011, "admin2Name": "Kikwit", "marketId": 1597, "marketLatitude": -5.0386111, "marketLocalName": null, "marketLongitude": 18.8180556, "marketName": "Kikwit"}, {"admin1Code": 900148, "admin1Name": "Kwilu", "admin2Code": 1003043, "admin2Name": "Masi-Manimba city", "marketId": 4126, "marketLatitude": -4.773883333, "marketLocalName": null, "marketLongitude": 17.88507667, "marketName": "Central de Masimanimba"}, {"admin1Code": 900164, "admin1Name": "Lomami", "admin2Code": 1003083, "admin2Name": "Kabinda city", "marketId": 4145, "marketLatitude": -6.139523333, "marketLocalName": null, "marketLongitude": 24.48483167, "marketName": "Central de Kabinda"}, {"admin1Code": 900164, "admin1Name": "Lomami", "admin2Code": 1003014, "admin2Name": "Mwene-Ditu", "marketId": 1603, "marketLatitude": -7.0, "marketLocalName": null, "marketLongitude": 23.45, "marketName": "Mwene-Ditu"}, {"admin1Code": 900159, "admin1Name": "Lualaba", "admin2Code": 1003015, "admin2Name": "Kolwezi", "marketId": 1605, "marketLatitude": -10.7166667, "marketLocalName": null, "marketLongitude": 25.4725, "marketName": "Kolwezi"}, {"admin1Code": 900159, "admin1Name": "Lualaba", "admin2Code": 1002947, "admin2Name": "Mutshatsha", "marketId": 1610, "marketLatitude": -11.0783, "marketLocalName": null, "marketLongitude": 24.51371, "marketName": "Dungu"}, {"admin1Code": 900159, "admin1Name": "Lualaba", "admin2Code": 1002950, "admin2Name": "Sandoa", "marketId": 4142, "marketLatitude": -9.695815, "marketLocalName": null, "marketLongitude": 22.87156, "marketName": "Sandoa"}, {"admin1Code": 900159, "admin1Name": "Lualaba", "admin2Code": 1002950, "admin2Name": "Sandoa", "marketId": 4143, "marketLatitude": -9.73317, "marketLocalName": null, "marketLongitude": 23.076885, "marketName": "Tshimbalanga"}, {"admin1Code": 900158, "admin1Name": "Maniema", "admin2Code": 1002994, "admin2Name": "Kabambare", "marketId": 4136, "marketLatitude": -4.185248333, "marketLocalName": null, "marketLongitude": 27.333505, "marketName": "Kayembe"}, {"admin1Code": 900158, "admin1Name": "Maniema", "admin2Code": 1002994, "admin2Name": "Kabambare", "marketId": 4137, "marketLatitude": -4.216463333, "marketLocalName": null, "marketLongitude": 27.112125, "marketName": "Wamaza"}, {"admin1Code": 900158, "admin1Name": "Maniema", "admin2Code": 1002945, "admin2Name": "Kailo", "marketId": 4135, "marketLatitude": -2.883326667, "marketLocalName": null, "marketLongitude": 26.07511167, "marketName": "Nyoka"}, {"admin1Code": 900158, "admin1Name": "Maniema", "admin2Code": 1003077, "admin2Name": "Kasongo city", "marketId": 4138, "marketLatitude": -4.426381667, "marketLocalName": null, "marketLongitude": 26.66774167, "marketName": "Limanga"}, {"admin1Code": 900158, "admin1Name": "Maniema", "admin2Code": 1002943, "admin2Name": "Kibombo", "marketId": 4139, "marketLatitude": -3.921846667, "marketLocalName": null, "marketLongitude": 25.92246833, "marketName": "Kibombo"}, {"admin1Code": 900158, "admin1Name": "Maniema", "admin2Code": 1002943, "admin2Name": "Kibombo", "marketId": 4140, "marketLatitude": -4.273813333, "marketLocalName": null, "marketLongitude": 26.010565, "marketName": "Likeri"}, {"admin1Code": 900158, "admin1Name": "Maniema", "admin2Code": 1003000, "admin2Name": "Kindu", "marketId": 149, "marketLatitude": -2.95, "marketLocalName": null, "marketLongitude": 25.95, "marketName": "Kindu"}, {"admin1Code": 900157, "admin1Name": "Nord-Kivu", "admin2Code": 1003024, "admin2Name": "Beni", "marketId": 1607, "marketLatitude": 0.5, "marketLocalName": null, "marketLongitude": 29.4666667, "marketName": "Beni"}, {"admin1Code": 900157, "admin1Name": "Nord-Kivu", "admin2Code": 1003023, "admin2Name": "Butembo", "marketId": 1650, "marketLatitude": 0.15, "marketLocalName": null, "marketLongitude": 29.2833333, "marketName": "Butembo"}, {"admin1Code": 900157, "admin1Name": "Nord-Kivu", "admin2Code": 1003021, "admin2Name": "Goma", "marketId": 3036, "marketLatitude": -1.6625, "marketLocalName": null, "marketLongitude": 29.20416667, "marketName": "Alanine"}, {"admin1Code": 900157, "admin1Name": "Nord-Kivu", "admin2Code": 1003021, "admin2Name": "Goma", "marketId": 3037, "marketLatitude": -1.680277778, "marketLocalName": null, "marketLongitude": 29.24111111, "marketName": "Birere"}, {"admin1Code": 900157, "admin1Name": "Nord-Kivu", "admin2Code": 1003021, "admin2Name": "Goma", "marketId": 152, "marketLatitude": -1.679167, "marketLocalName": null, "marketLongitude": 29.222778, "marketName": "Goma"}, {"admin1Code": 900157, "admin1Name": "Nord-Kivu", "admin2Code": 1003021, "admin2Name": "Goma", "marketId": 3035, "marketLatitude": -1.6675, "marketLocalName": null, "marketLongitude": 29.23416667, "marketName": "Virunga"}, {"admin1Code": 900157, "admin1Name": "Nord-Kivu", "admin2Code": 1002942, "admin2Name": "Masisi", "marketId": 3210, "marketLatitude": -1.4050971, "marketLocalName": null, "marketLongitude": 28.85975103, "marketName": "Lushebere"}, {"admin1Code": 900157, "admin1Name": "Nord-Kivu", "admin2Code": 1002942, "admin2Name": "Masisi", "marketId": 3211, "marketLatitude": -1.39625596, "marketLocalName": null, "marketLongitude": 28.81977669, "marketName": "Masisi Centre"}, {"admin1Code": 900157, "admin1Name": "Nord-Kivu", "admin2Code": 1002942, "admin2Name": "Masisi", "marketId": 3044, "marketLatitude": -1.661388889, "marketLocalName": null, "marketLongitude": 28.98547222, "marketName": "Mukwidja"}, {"admin1Code": 900157, "admin1Name": "Nord-Kivu", "admin2Code": 1002938, "admin2Name": "Nyiragongo", "marketId": 3038, "marketLatitude": -1.609722222, "marketLocalName": null, "marketLongitude": 29.15555556, "marketName": "Mugunga3"}, {"admin1Code": 900157, "admin1Name": "Nord-Kivu", "admin2Code": 1002938, "admin2Name": "Nyiragongo", "marketId": 3039, "marketLatitude": -1.511388889, "marketLocalName": null, "marketLongitude": 29.32444444, "marketName": "Nyiragongo"}, {"admin1Code": 900157, "admin1Name": "Nord-Kivu", "admin2Code": 1002941, "admin2Name": "Rutshuru", "marketId": 2312, "marketLatitude": -1.132638931274414, "marketLocalName": null, "marketLongitude": 29.042449951171875, "marketName": "Mweso"}, {"admin1Code": 900157, "admin1Name": "Nord-Kivu", "admin2Code": 1002941, "admin2Name": "Rutshuru", "marketId": 2313, "marketLatitude": -1.02133047580719, "marketLocalName": null, "marketLongitude": 29.11354637145996, "marketName": "Nyanzale"}, {"admin1Code": 900152, "admin1Name": "Nord-Ubangi", "admin2Code": 1003019, "admin2Name": "Gbadolite", "marketId": 1649, "marketLatitude": 4.2833333, "marketLocalName": null, "marketLongitude": 21.0166667, "marketName": "Gbadolite"}, {"admin1Code": 900152, "admin1Name": "Nord-Ubangi", "admin2Code": 1002903, "admin2Name": "Mobayi-Mbongo", "marketId": 2262, "marketLatitude": 4.08174991607666, "marketLocalName": null, "marketLongitude": 20.762710571289062, "marketName": "Inke"}, {"admin1Code": 900163, "admin1Name": "Sankuru", "admin2Code": 1002974, "admin2Name": "Lomela", "marketId": 4149, "marketLatitude": -2.392616667, "marketLocalName": null, "marketLongitude": 23.31300667, "marketName": "Lokolo"}, {"admin1Code": 900167, "admin1Name": "Sud-Kivu", "admin2Code": 1003020, "admin2Name": "Bukavu", "marketId": 150, "marketLatitude": -2.508333, "marketLocalName": null, "marketLongitude": 28.860833, "marketName": "Bukavu"}, {"admin1Code": 900167, "admin1Name": "Sud-Kivu", "admin2Code": 1003020, "admin2Name": "Bukavu", "marketId": 3975, "marketLatitude": -2.5201, "marketLocalName": null, "marketLongitude": 28.8516, "marketName": "Kadutu"}, {"admin1Code": 900167, "admin1Name": "Sud-Kivu", "admin2Code": 1002996, "admin2Name": "Fizi", "marketId": 2304, "marketLatitude": -4.102112770080566, "marketLocalName": null, "marketLongitude": 29.095779418945312, "marketName": "Baraka"}, {"admin1Code": 900167, "admin1Name": "Sud-Kivu", "admin2Code": 1002996, "admin2Name": "Fizi", "marketId": 2268, "marketLatitude": -3.7821121215820312, "marketLocalName": null, "marketLongitude": 29.093477249145508, "marketName": "Lusenda"}, {"admin1Code": 900167, "admin1Name": "Sud-Kivu", "admin2Code": 1003022, "admin2Name": "Idjwi", "marketId": 4133, "marketLatitude": -2.095512557, "marketLocalName": null, "marketLongitude": 29.04211418, "marketName": "Chikoma"}, {"admin1Code": 900167, "admin1Name": "Sud-Kivu", "admin2Code": 1003022, "admin2Name": "Idjwi", "marketId": 4134, "marketLatitude": -2.017198384, "marketLocalName": null, "marketLongitude": 29.06561246, "marketName": "Kishenyi"}, {"admin1Code": 900167, "admin1Name": "Sud-Kivu", "admin2Code": 1003022, "admin2Name": "Idjwi", "marketId": 3043, "marketLatitude": -2.17325, "marketLocalName": null, "marketLongitude": 29.01691667, "marketName": "Minova"}, {"admin1Code": 900167, "admin1Name": "Sud-Kivu", "admin2Code": 1003003, "admin2Name": "Kabare", "marketId": 3042, "marketLatitude": -2.1725, "marketLocalName": null, "marketLongitude": 28.85416667, "marketName": "Kabamba"}, {"admin1Code": 900167, "admin1Name": "Sud-Kivu", "admin2Code": 1003003, "admin2Name": "Kabare", "marketId": 4131, "marketLatitude": -2.29642671, "marketLocalName": null, "marketLongitude": 28.79887846, "marketName": "Kavumu"}, {"admin1Code": 900167, "admin1Name": "Sud-Kivu", "admin2Code": 1003003, "admin2Name": "Kabare", "marketId": 4132, "marketLatitude": -2.40164366, "marketLocalName": null, "marketLongitude": 28.81221742, "marketName": "Mudaka"}, {"admin1Code": 900167, "admin1Name": "Sud-Kivu", "admin2Code": 1003067, "admin2Name": "Kamituga", "marketId": 3969, "marketLatitude": -3.064993333, "marketLocalName": null, "marketLongitude": 28.18509167, "marketName": "Kamituga"}, {"admin1Code": 900167, "admin1Name": "Sud-Kivu", "admin2Code": 1003001, "admin2Name": "Mwenga", "marketId": 3972, "marketLatitude": -2.940095, "marketLocalName": null, "marketLongitude": 28.52544, "marketName": "Kasika"}, {"admin1Code": 900167, "admin1Name": "Sud-Kivu", "admin2Code": 1003001, "admin2Name": "Mwenga", "marketId": 4522, "marketLatitude": -2.999786, "marketLocalName": null, "marketLongitude": 28.466281, "marketName": "Kibumba"}, {"admin1Code": 900167, "admin1Name": "Sud-Kivu", "admin2Code": 1003001, "admin2Name": "Mwenga", "marketId": 3968, "marketLatitude": -2.88809, "marketLocalName": null, "marketLongitude": 28.57328667, "marketName": "Kilungutwe"}, {"admin1Code": 900167, "admin1Name": "Sud-Kivu", "admin2Code": 1003001, "admin2Name": "Mwenga", "marketId": 3971, "marketLatitude": -3.028333, "marketLocalName": null, "marketLongitude": 28.441435, "marketName": "Mwenga"}, {"admin1Code": 900167, "admin1Name": "Sud-Kivu", "admin2Code": 1003002, "admin2Name": "Walungu", "marketId": 3973, "marketLatitude": -2.696631, "marketLocalName": null, "marketLongitude": 28.548433, "marketName": "Kakinda"}, {"admin1Code": 900167, "admin1Name": "Sud-Kivu", "admin2Code": 1003002, "admin2Name": "Walungu", "marketId": 3962, "marketLatitude": -2.59443, "marketLocalName": null, "marketLongitude": 28.61702667, "marketName": "Kaniola"}, {"admin1Code": 900167, "admin1Name": "Sud-Kivu", "admin2Code": 1003002, "admin2Name": "Walungu", "marketId": 3959, "marketLatitude": -2.582215, "marketLocalName": null, "marketLongitude": 28.75418, "marketName": "Mugogo"}, {"admin1Code": 900167, "admin1Name": "Sud-Kivu", "admin2Code": 1003002, "admin2Name": "Walungu", "marketId": 3960, "marketLatitude": -2.619071, "marketLocalName": null, "marketLongitude": 28.680348, "marketName": "Walungu"}, {"admin1Code": 900151, "admin1Name": "Sud-Ubangi", "admin2Code": 1002902, "admin2Name": "Libenge", "marketId": 3034, "marketLatitude": 3.717505556, "marketLocalName": null, "marketLongitude": 18.76996111, "marketName": "Boyabu"}, {"admin1Code": 900151, "admin1Name": "Sud-Ubangi", "admin2Code": 1002902, "admin2Name": "Libenge", "marketId": 2306, "marketLatitude": 3.649027109146118, "marketLocalName": null, "marketLongitude": 18.635231018066406, "marketName": "Libenge"}, {"admin1Code": 900151, "admin1Name": "Sud-Ubangi", "admin2Code": 1003007, "admin2Name": "Zongo", "marketId": 2263, "marketLatitude": 4.145100116729736, "marketLocalName": null, "marketLongitude": 18.79145050048828, "marketName": "Mole"}, {"admin1Code": 900161, "admin1Name": "Tanganyika", "admin2Code": 1002959, "admin2Name": "Kabalo", "marketId": 2668, "marketLatitude": -6.05494, "marketLocalName": null, "marketLongitude": 26.92469, "marketName": "Centrale"}, {"admin1Code": 900161, "admin1Name": "Tanganyika", "admin2Code": 1002959, "admin2Name": "Kabalo", "marketId": 148, "marketLatitude": -6.05, "marketLocalName": null, "marketLongitude": 26.916667, "marketName": "Kabalo"}, {"admin1Code": 900161, "admin1Name": "Tanganyika", "admin2Code": 1002959, "admin2Name": "Kabalo", "marketId": 2669, "marketLatitude": -6.21628, "marketLocalName": null, "marketLongitude": 26.34524, "marketName": "Katutu"}, {"admin1Code": 900161, "admin1Name": "Tanganyika", "admin2Code": 1002959, "admin2Name": "Kabalo", "marketId": 2670, "marketLatitude": -5.7425, "marketLocalName": null, "marketLongitude": 26.94714, "marketName": "Kitule gare"}, {"admin1Code": 900161, "admin1Name": "Tanganyika", "admin2Code": 1002959, "admin2Name": "Kabalo", "marketId": 2671, "marketLatitude": -6.19046, "marketLocalName": null, "marketLongitude": 26.8900799999999, "marketName": "Mosantu premier"}, {"admin1Code": 900161, "admin1Name": "Tanganyika", "admin2Code": 1002959, "admin2Name": "Kabalo", "marketId": 2672, "marketLatitude": -6.40367, "marketLocalName": null, "marketLongitude": 26.72172, "marketName": "Ngwena gare"}, {"admin1Code": 900161, "admin1Name": "Tanganyika", "admin2Code": 1002959, "admin2Name": "Kabalo", "marketId": 2673, "marketLatitude": -6.06083, "marketLocalName": null, "marketLongitude": 26.9363599999999, "marketName": "Pongo"}, {"admin1Code": 900161, "admin1Name": "Tanganyika", "admin2Code": 1002957, "admin2Name": "Kalemie", "marketId": 143, "marketLatitude": -5.923004, "marketLocalName": null, "marketLongitude": 29.194574, "marketName": "Kalemie"}, {"admin1Code": 900161, "admin1Name": "Tanganyika", "admin2Code": 1003101, "admin2Name": "Kaoze", "marketId": 1395, "marketLatitude": -7.04, "marketLocalName": null, "marketLongitude": 29.76, "marketName": "Moba"}, {"admin1Code": 900161, "admin1Name": "Tanganyika", "admin2Code": 1002993, "admin2Name": "Moba", "marketId": 4144, "marketLatitude": -7.072275, "marketLocalName": null, "marketLongitude": 29.73406, "marketName": "Kirungu"}, {"admin1Code": 900144, "admin1Name": "Tshopo", "admin2Code": 1002916, "admin2Name": "Banalia", "marketId": 4129, "marketLatitude": 1.001438333, "marketLocalName": null, "marketLongitude": 25.242445, "marketName": "Belgika"}, {"admin1Code": 900144, "admin1Name": "Tshopo", "admin2Code": 1002916, "admin2Name": "Banalia", "marketId": 4130, "marketLatitude": 1.556031667, "marketLocalName": null, "marketLongitude": 25.31858833, "marketName": "Central de Banalia"}, {"admin1Code": 900144, "admin1Name": "Tshopo", "admin2Code": 1003052, "admin2Name": "Basoko city", "marketId": 1600, "marketLatitude": 1.2333333, "marketLocalName": null, "marketLongitude": 23.6, "marketName": "Basoko"}, {"admin1Code": 900144, "admin1Name": "Tshopo", "admin2Code": 1003018, "admin2Name": "Kisangani", "marketId": 1608, "marketLatitude": 0.5166667, "marketLocalName": null, "marketLongitude": 25.2, "marketName": "Kisangani"}, {"admin1Code": 900154, "admin1Name": "Tshuapa", "admin2Code": 1002911, "admin2Name": "Befale", "marketId": 4128, "marketLatitude": 0.3941622, "marketLocalName": null, "marketLongitude": 20.84295647, "marketName": "Central de Befale"}], "page": 1, "totalItems": 144}