{"items": [{"adm0Code": 73, "commodityDateMonth": 2, "commodityDateWeek": null, "commodityDateYear": 2021, "commodityID": 136, "commodityName": "Maize (yellow)", "commodityPrice": 0.0, "commodityPriceDate": "2021-02-15T00:00:00", "commodityPriceFlag": "forecast", "commodityPriceObservations": null, "commodityPriceSourceName": "", "commodityUnitID": 93, "commodityUnitName": "100 Pounds", "countryISO3": "ECU", "countryName": "Ecuador", "currencyID": 28, "currencyName": "USD", "marketID": 2596, "marketName": "Portoviejo", "originalFrequency": "monthly", "priceTypeID": 14, "priceTypeName": "Wholesale"}, {"adm0Code": 73, "commodityDateMonth": 6, "commodityDateWeek": null, "commodityDateYear": 2020, "commodityID": 83, "commodityName": "Potatoes", "commodityPrice": 0.0, "commodityPriceDate": "2020-06-15T00:00:00", "commodityPriceFlag": "forecast", "commodityPriceObservations": null, "commodityPriceSourceName": "", "commodityUnitID": 5, "commodityUnitName": "KG", "countryISO3": "ECU", "countryName": "Ecuador", "currencyID": 28, "currencyName": "USD", "marketID": 2582, "marketName": "Guayaquil", "originalFrequency": "monthly", "priceTypeID": 14, "priceTypeName": "Wholesale"}, {"adm0Code": 73, "commodityDateMonth": 8, "commodityDateWeek": null, "commodityDateYear": 2020, "commodityID": 83, "commodityName": "Potatoes", "commodityPrice": 0.0, "commodityPriceDate": "2020-08-15T00:00:00", "commodityPriceFlag": "forecast", "commodityPriceObservations": null, "commodityPriceSourceName": "", "commodityUnitID": 5, "commodityUnitName": "KG", "countryISO3": "ECU", "countryName": "Ecuador", "currencyID": 28, "currencyName": "USD", "marketID": 2582, "marketName": "Guayaquil", "originalFrequency": "monthly", "priceTypeID": 14, "priceTypeName": "Wholesale"}, {"adm0Code": 73, "commodityDateMonth": 3, "commodityDateWeek": null, "commodityDateYear": 2021, "commodityID": 51, "commodityName": "Maize", "commodityPrice": 0.0, "commodityPriceDate": "2021-03-15T00:00:00", "commodityPriceFlag": "forecast", "commodityPriceObservations": null, "commodityPriceSourceName": "", "commodityUnitID": 5, "commodityUnitName": "KG", "countryISO3": "ECU", "countryName": "Ecuador", "currencyID": 28, "currencyName": "USD", "marketID": 2573, "marketName": "Cuenca", "originalFrequency": "monthly", "priceTypeID": 14, "priceTypeName": "Wholesale"}, {"adm0Code": 73, "commodityDateMonth": 7, "commodityDateWeek": null, "commodityDateYear": 2017, "commodityID": 162, "commodityName": "Rice (long grain)", "commodityPrice": 0.0, "commodityPriceDate": "2017-07-15T00:00:00", "commodityPriceFlag": "forecast", "commodityPriceObservations": null, "commodityPriceSourceName": "", "commodityUnitID": 5, "commodityUnitName": "KG", "countryISO3": "ECU", "countryName": "Ecuador", "currencyID": 28, "currencyName": "USD", "marketID": 2563, "marketName": "Ambato", "originalFrequency": "monthly", "priceTypeID": 14, "priceTypeName": "Wholesale"}, {"adm0Code": 73, "commodityDateMonth": 9, "commodityDateWeek": null, "commodityDateYear": 2020, "commodityID": 136, "commodityName": "Maize (yellow)", "commodityPrice": 0.0, "commodityPriceDate": "2020-09-15T00:00:00", "commodityPriceFlag": "forecast", "commodityPriceObservations": null, "commodityPriceSourceName": "", "commodityUnitID": 93, "commodityUnitName": "100 Pounds", "countryISO3": "ECU", "countryName": "Ecuador", "currencyID": 28, "currencyName": "USD", "marketID": 2596, "marketName": "Portoviejo", "originalFrequency": "monthly", "priceTypeID": 14, "priceTypeName": "Wholesale"}, {"adm0Code": 73, "commodityDateMonth": 9, "commodityDateWeek": null, "commodityDateYear": 2020, "commodityID": 51, "commodityName": "Maize", "commodityPrice": 0.0, "commodityPriceDate": "2020-09-15T00:00:00", "commodityPriceFlag": "forecast", "commodityPriceObservations": null, "commodityPriceSourceName": "", "commodityUnitID": 5, "commodityUnitName": "KG", "countryISO3": "ECU", "countryName": "Ecuador", "currencyID": 28, "currencyName": "USD", "marketID": 2582, "marketName": "Guayaquil", "originalFrequency": "monthly", "priceTypeID": 14, "priceTypeName": "Wholesale"}, {"adm0Code": 73, "commodityDateMonth": 2, "commodityDateWeek": null, "commodityDateYear": 2021, "commodityID": 83, "commodityName": "Potatoes", "commodityPrice": 0.0, "commodityPriceDate": "2021-02-15T00:00:00", "commodityPriceFlag": "forecast", "commodityPriceObservations": null, "commodityPriceSourceName": "", "commodityUnitID": 5, "commodityUnitName": "KG", "countryISO3": "ECU", "countryName": "Ecuador", "currencyID": 28, "currencyName": "USD", "marketID": 2573, "marketName": "Cuenca", "originalFrequency": "monthly", "priceTypeID": 14, "priceTypeName": "Wholesale"}, {"adm0Code": 73, "commodityDateMonth": 6, "commodityDateWeek": null, "commodityDateYear": 2020, "commodityID": 599, "commodityName": "Wheat (imported)", "commodityPrice": 0.0, "commodityPriceDate": "2020-06-15T00:00:00", "commodityPriceFlag": "forecast", "commodityPriceObservations": null, "commodityPriceSourceName": "", "commodityUnitID": 93, "commodityUnitName": "100 Pounds", "countryISO3": "ECU", "countryName": "Ecuador", "currencyID": 28, "currencyName": "USD", "marketID": 2598, "marketName": "Quito", "originalFrequency": "monthly", "priceTypeID": 14, "priceTypeName": "Wholesale"}, {"adm0Code": 73, "commodityDateMonth": 10, "commodityDateWeek": null, "commodityDateYear": 2017, "commodityID": 58, "commodityName": "Wheat flour", "commodityPrice": 0.0, "commodityPriceDate": "2017-10-15T00:00:00", "commodityPriceFlag": "forecast", "commodityPriceObservations": null, "commodityPriceSourceName": "", "commodityUnitID": 5, "commodityUnitName": "KG", "countryISO3": "ECU", "countryName": "Ecuador", "currencyID": 28, "currencyName": "USD", "marketID": 2596, "marketName": "Portoviejo", "originalFrequency": "monthly", "priceTypeID": 14, "priceTypeName": "Wholesale"}, {"adm0Code": 73, "commodityDateMonth": 5, "commodityDateWeek": null, "commodityDateYear": 2021, "commodityID": 162, "commodityName": "Rice (long grain)", "commodityPrice": 0.0, "commodityPriceDate": "2021-05-15T00:00:00", "commodityPriceFlag": "forecast", "commodityPriceObservations": null, "commodityPriceSourceName": "", "commodityUnitID": 5, "commodityUnitName": "KG", "countryISO3": "ECU", "countryName": "Ecuador", "currencyID": 28, "currencyName": "USD", "marketID": 2573, "marketName": "Cuenca", "originalFrequency": "monthly", "priceTypeID": 14, "priceTypeName": "Wholesale"}, {"adm0Code": 73, "commodityDateMonth": 4, "commodityDateWeek": null, "commodityDateYear": 2020, "commodityID": 136, "commodityName": "Maize (yellow)", "commodityPrice": 0.0, "commodityPriceDate": "2020-04-15T00:00:00", "commodityPriceFlag": "forecast", "commodityPriceObservations": null, "commodityPriceSourceName": "", "commodityUnitID": 93, "commodityUnitName": "100 Pounds", "countryISO3": "ECU", "countryName": "Ecuador", "currencyID": 28, "currencyName": "USD", "marketID": 2582, "marketName": "Guayaquil", "originalFrequency": "monthly", "priceTypeID": 14, "priceTypeName": "Wholesale"}, {"adm0Code": 73, "commodityDateMonth": 8, "commodityDateWeek": null, "commodityDateYear": 2017, "commodityID": 162, "commodityName": "Rice (long grain)", "commodityPrice": 0.0, "commodityPriceDate": "2017-08-15T00:00:00", "commodityPriceFlag": "forecast", "commodityPriceObservations": null, "commodityPriceSourceName": "", "commodityUnitID": 5, "commodityUnitName": "KG", "countryISO3": "ECU", "countryName": "Ecuador", "currencyID": 28, "currencyName": "USD", "marketID": 2563, "marketName": "Ambato", "originalFrequency": "monthly", "priceTypeID": 14, "priceTypeName": "Wholesale"}, {"adm0Code": 73, "commodityDateMonth": 6, "commodityDateWeek": null, "commodityDateYear": 2017, "commodityID": 162, "commodityName": "Rice (long grain)", "commodityPrice": 0.0, "commodityPriceDate": "2017-06-15T00:00:00", "commodityPriceFlag": "forecast", "commodityPriceObservations": null, "commodityPriceSourceName": "", "commodityUnitID": 5, "commodityUnitName": "KG", "countryISO3": "ECU", "countryName": "Ecuador", "currencyID": 28, "currencyName": "USD", "marketID": 2596, "marketName": "Portoviejo", "originalFrequency": "monthly", "priceTypeID": 14, "priceTypeName": "Wholesale"}, {"adm0Code": 73, "commodityDateMonth": 2, "commodityDateWeek": null, "commodityDateYear": 2021, "commodityID": 51, "commodityName": "Maize", "commodityPrice": 0.0, "commodityPriceDate": "2021-02-15T00:00:00", "commodityPriceFlag": "forecast", "commodityPriceObservations": null, "commodityPriceSourceName": "", "commodityUnitID": 5, "commodityUnitName": "KG", "countryISO3": "ECU", "countryName": "Ecuador", "currencyID": 28, "currencyName": "USD", "marketID": 2563, "marketName": "Ambato", "originalFrequency": "monthly", "priceTypeID": 14, "priceTypeName": "Wholesale"}, {"adm0Code": 73, "commodityDateMonth": 12, "commodityDateWeek": null, "commodityDateYear": 2020, "commodityID": 136, "commodityName": "Maize (yellow)", "commodityPrice": 0.0, "commodityPriceDate": "2020-12-15T00:00:00", "commodityPriceFlag": "forecast", "commodityPriceObservations": null, "commodityPriceSourceName": "", "commodityUnitID": 93, "commodityUnitName": "100 Pounds", "countryISO3": "ECU", "countryName": "Ecuador", "currencyID": 28, "currencyName": "USD", "marketID": 2596, "marketName": "Portoviejo", "originalFrequency": "monthly", "priceTypeID": 14, "priceTypeName": "Wholesale"}, {"adm0Code": 73, "commodityDateMonth": 5, "commodityDateWeek": null, "commodityDateYear": 2021, "commodityID": 83, "commodityName": "Potatoes", "commodityPrice": 0.0, "commodityPriceDate": "2021-05-15T00:00:00", "commodityPriceFlag": "forecast", "commodityPriceObservations": null, "commodityPriceSourceName": "", "commodityUnitID": 5, "commodityUnitName": "KG", "countryISO3": "ECU", "countryName": "Ecuador", "currencyID": 28, "currencyName": "USD", "marketID": 2573, "marketName": "Cuenca", "originalFrequency": "monthly", "priceTypeID": 14, "priceTypeName": "Wholesale"}, {"adm0Code": 73, "commodityDateMonth": 8, "commodityDateWeek": null, "commodityDateYear": 2021, "commodityID": 162, "commodityName": "Rice (long grain)", "commodityPrice": 0.0, "commodityPriceDate": "2021-08-15T00:00:00", "commodityPriceFlag": "forecast", "commodityPriceObservations": null, "commodityPriceSourceName": "", "commodityUnitID": 5, "commodityUnitName": "KG", "countryISO3": "ECU", "countryName": "Ecuador", "currencyID": 28, "currencyName": "USD", "marketID": 2598, "marketName": "Quito", "originalFrequency": "monthly", "priceTypeID": 14, "priceTypeName": "Wholesale"}, {"adm0Code": 73, "commodityDateMonth": 9, "commodityDateWeek": null, "commodityDateYear": 2021, "commodityID": 162, "commodityName": "Rice (long grain)", "commodityPrice": 0.0, "commodityPriceDate": "2021-09-15T00:00:00", "commodityPriceFlag": "forecast", "commodityPriceObservations": null, "commodityPriceSourceName": "", "commodityUnitID": 5, "commodityUnitName": "KG", "countryISO3": "ECU", "countryName": "Ecuador", "currencyID": 28, "currencyName": "USD", "marketID": 2598, "marketName": "Quito", "originalFrequency": "monthly", "priceTypeID": 14, "priceTypeName": "Wholesale"}, {"adm0Code": 73, "commodityDateMonth": 5, "commodityDateWeek": null, "commodityDateYear": 2021, "commodityID": 51, "commodityName": "Maize", "commodityPrice": 0.0, "commodityPriceDate": "2021-05-15T00:00:00", "commodityPriceFlag": "forecast", "commodityPriceObservations": null, "commodityPriceSourceName": "", "commodityUnitID": 5, "commodityUnitName": "KG", "countryISO3": "ECU", "countryName": "Ecuador", "currencyID": 28, "currencyName": "USD", "marketID": 2573, "marketName": "Cuenca", "originalFrequency": "monthly", "priceTypeID": 14, "priceTypeName": "Wholesale"}, {"adm0Code": 73, "commodityDateMonth": 6, "commodityDateWeek": null, "commodityDateYear": 2020, "commodityID": 51, "commodityName": "Maize", "commodityPrice": 0.0, "commodityPriceDate": "2020-06-15T00:00:00", "commodityPriceFlag": "forecast", "commodityPriceObservations": null, "commodityPriceSourceName": "", "commodityUnitID": 5, "commodityUnitName": "KG", "countryISO3": "ECU", "countryName": "Ecuador", "currencyID": 28, "currencyName": "USD", "marketID": 2598, "marketName": "Quito", "originalFrequency": "monthly", "priceTypeID": 14, "priceTypeName": "Wholesale"}, {"adm0Code": 73, "commodityDateMonth": 9, "commodityDateWeek": null, "commodityDateYear": 2020, "commodityID": 136, "commodityName": "Maize (yellow)", "commodityPrice": 0.0, "commodityPriceDate": "2020-09-15T00:00:00", "commodityPriceFlag": "forecast", "commodityPriceObservations": null, "commodityPriceSourceName": "", "commodityUnitID": 93, "commodityUnitName": "100 Pounds", "countryISO3": "ECU", "countryName": "Ecuador", "currencyID": 28, "currencyName": "USD", "marketID": 2598, "marketName": "Quito", "originalFrequency": "monthly", "priceTypeID": 14, "priceTypeName": "Wholesale"}, {"adm0Code": 73, "commodityDateMonth": 6, "commodityDateWeek": null, "commodityDateYear": 2020, "commodityID": 58, "commodityName": "Wheat flour", "commodityPrice": 0.0, "commodityPriceDate": "2020-06-15T00:00:00", "commodityPriceFlag": "forecast", "commodityPriceObservations": null, "commodityPriceSourceName": "", "commodityUnitID": 22, "commodityUnitName": "50 KG", "countryISO3": "ECU", "countryName": "Ecuador", "currencyID": 28, "currencyName": "USD", "marketID": 2598, "marketName": "Quito", "originalFrequency": "monthly", "priceTypeID": 14, "priceTypeName": "Wholesale"}, {"adm0Code": 73, "commodityDateMonth": 5, "commodityDateWeek": null, "commodityDateYear": 2020, "commodityID": 136, "commodityName": "Maize (yellow)", "commodityPrice": 0.0, "commodityPriceDate": "2020-05-15T00:00:00", "commodityPriceFlag": "forecast", "commodityPriceObservations": null, "commodityPriceSourceName": "", "commodityUnitID": 93, "commodityUnitName": "100 Pounds", "countryISO3": "ECU", "countryName": "Ecuador", "currencyID": 28, "currencyName": "USD", "marketID": 2582, "marketName": "Guayaquil", "originalFrequency": "monthly", "priceTypeID": 14, "priceTypeName": "Wholesale"}, {"adm0Code": 73, "commodityDateMonth": 10, "commodityDateWeek": null, "commodityDateYear": 2020, "commodityID": 136, "commodityName": "Maize (yellow)", "commodityPrice": 0.0, "commodityPriceDate": "2020-10-15T00:00:00", "commodityPriceFlag": "forecast", "commodityPriceObservations": null, "commodityPriceSourceName": "", "commodityUnitID": 93, "commodityUnitName": "100 Pounds", "countryISO3": "ECU", "countryName": "Ecuador", "currencyID": 28, "currencyName": "USD", "marketID": 2596, "marketName": "Portoviejo", "originalFrequency": "monthly", "priceTypeID": 14, "priceTypeName": "Wholesale"}, {"adm0Code": 73, "commodityDateMonth": 5, "commodityDateWeek": null, "commodityDateYear": 2020, "commodityID": 51, "commodityName": "Maize", "commodityPrice": 0.0, "commodityPriceDate": "2020-05-15T00:00:00", "commodityPriceFlag": "forecast", "commodityPriceObservations": null, "commodityPriceSourceName": "", "commodityUnitID": 5, "commodityUnitName": "KG", "countryISO3": "ECU", "countryName": "Ecuador", "currencyID": 28, "currencyName": "USD", "marketID": 2582, "marketName": "Guayaquil", "originalFrequency": "monthly", "priceTypeID": 14, "priceTypeName": "Wholesale"}, {"adm0Code": 73, "commodityDateMonth": 4, "commodityDateWeek": null, "commodityDateYear": 2021, "commodityID": 51, "commodityName": "Maize", "commodityPrice": 0.0, "commodityPriceDate": "2021-04-15T00:00:00", "commodityPriceFlag": "forecast", "commodityPriceObservations": null, "commodityPriceSourceName": "", "commodityUnitID": 5, "commodityUnitName": "KG", "countryISO3": "ECU", "countryName": "Ecuador", "currencyID": 28, "currencyName": "USD", "marketID": 2599, "marketName": "Riobamba", "originalFrequency": "monthly", "priceTypeID": 14, "priceTypeName": "Wholesale"}, {"adm0Code": 73, "commodityDateMonth": 9, "commodityDateWeek": null, "commodityDateYear": 2020, "commodityID": 599, "commodityName": "Wheat (imported)", "commodityPrice": 0.0, "commodityPriceDate": "2020-09-15T00:00:00", "commodityPriceFlag": "forecast", "commodityPriceObservations": null, "commodityPriceSourceName": "", "commodityUnitID": 93, "commodityUnitName": "100 Pounds", "countryISO3": "ECU", "countryName": "Ecuador", "currencyID": 28, "currencyName": "USD", "marketID": 2598, "marketName": "Quito", "originalFrequency": "monthly", "priceTypeID": 14, "priceTypeName": "Wholesale"}, {"adm0Code": 73, "commodityDateMonth": 5, "commodityDateWeek": null, "commodityDateYear": 2020, "commodityID": 83, "commodityName": "Potatoes", "commodityPrice": 0.0, "commodityPriceDate": "2020-05-15T00:00:00", "commodityPriceFlag": "forecast", "commodityPriceObservations": null, "commodityPriceSourceName": "", "commodityUnitID": 5, "commodityUnitName": "KG", "countryISO3": "ECU", "countryName": "Ecuador", "currencyID": 28, "currencyName": "USD", "marketID": 2582, "marketName": "Guayaquil", "originalFrequency": "monthly", "priceTypeID": 14, "priceTypeName": "Wholesale"}, {"adm0Code": 73, "commodityDateMonth": 7, "commodityDateWeek": null, "commodityDateYear": 2017, "commodityID": 58, "commodityName": "Wheat flour", "commodityPrice": 0.0, "commodityPriceDate": "2017-07-15T00:00:00", "commodityPriceFlag": "forecast", "commodityPriceObservations": null, "commodityPriceSourceName": "", "commodityUnitID": 5, "commodityUnitName": "KG", "countryISO3": "ECU", "countryName": "Ecuador", "currencyID": 28, "currencyName": "USD", "marketID": 2596, "marketName": "Portoviejo", "originalFrequency": "monthly", "priceTypeID": 14, "priceTypeName": "Wholesale"}, {"adm0Code": 73, "commodityDateMonth": 6, "commodityDateWeek": null, "commodityDateYear": 2021, "commodityID": 51, "commodityName": "Maize", "commodityPrice": 0.0, "commodityPriceDate": "2021-06-15T00:00:00", "commodityPriceFlag": "forecast", "commodityPriceObservations": null, "commodityPriceSourceName": "", "commodityUnitID": 5, "commodityUnitName": "KG", "countryISO3": "ECU", "countryName": "Ecuador", "currencyID": 28, "currencyName": "USD", "marketID": 2563, "marketName": "Ambato", "originalFrequency": "monthly", "priceTypeID": 14, "priceTypeName": "Wholesale"}, {"adm0Code": 73, "commodityDateMonth": 8, "commodityDateWeek": null, "commodityDateYear": 2020, "commodityID": 136, "commodityName": "Maize (yellow)", "commodityPrice": 0.0, "commodityPriceDate": "2020-08-15T00:00:00", "commodityPriceFlag": "forecast", "commodityPriceObservations": null, "commodityPriceSourceName": "", "commodityUnitID": 93, "commodityUnitName": "100 Pounds", "countryISO3": "ECU", "countryName": "Ecuador", "currencyID": 28, "currencyName": "USD", "marketID": 2598, "marketName": "Quito", "originalFrequency": "monthly", "priceTypeID": 14, "priceTypeName": "Wholesale"}, {"adm0Code": 73, "commodityDateMonth": 2, "commodityDateWeek": null, "commodityDateYear": 2021, "commodityID": 83, "commodityName": "Potatoes", "commodityPrice": 0.0, "commodityPriceDate": "2021-02-15T00:00:00", "commodityPriceFlag": "forecast", "commodityPriceObservations": null, "commodityPriceSourceName": "", "commodityUnitID": 5, "commodityUnitName": "KG", "countryISO3": "ECU", "countryName": "Ecuador", "currencyID": 28, "currencyName": "USD", "marketID": 2563, "marketName": "Ambato", "originalFrequency": "monthly", "priceTypeID": 14, "priceTypeName": "Wholesale"}, {"adm0Code": 73, "commodityDateMonth": 4, "commodityDateWeek": null, "commodityDateYear": 2020, "commodityID": 58, "commodityName": "Wheat flour", "commodityPrice": 0.0, "commodityPriceDate": "2020-04-15T00:00:00", "commodityPriceFlag": "forecast", "commodityPriceObservations": null, "commodityPriceSourceName": "", "commodityUnitID": 22, "commodityUnitName": "50 KG", "countryISO3": "ECU", "countryName": "Ecuador", "currencyID": 28, "currencyName": "USD", "marketID": 2598, "marketName": "Quito", "originalFrequency": "monthly", "priceTypeID": 14, "priceTypeName": "Wholesale"}, {"adm0Code": 73, "commodityDateMonth": 9, "commodityDateWeek": null, "commodityDateYear": 2017, "commodityID": 58, "commodityName": "Wheat flour", "commodityPrice": 0.0, "commodityPriceDate": "2017-09-15T00:00:00", "commodityPriceFlag": "forecast", "commodityPriceObservations": null, "commodityPriceSourceName": "", "commodityUnitID": 5, "commodityUnitName": "KG", "countryISO3": "ECU", "countryName": "Ecuador", "currencyID": 28, "currencyName": "USD", "marketID": 2596, "marketName": "Portoviejo", "originalFrequency": "monthly", "priceTypeID": 14, "priceTypeName": "Wholesale"}, {"adm0Code": 73, "commodityDateMonth": 7, "commodityDateWeek": null, "commodityDateYear": 2020, "commodityID": 58, "commodityName": "Wheat flour", "commodityPrice": 0.0, "commodityPriceDate": "2020-07-15T00:00:00", "commodityPriceFlag": "forecast", "commodityPriceObservations": null, "commodityPriceSourceName": "", "commodityUnitID": 22, "commodityUnitName": "50 KG", "countryISO3": "ECU", "countryName": "Ecuador", "currencyID": 28, "currencyName": "USD", "marketID": 2598, "marketName": "Quito", "originalFrequency": "monthly", "priceTypeID": 14, "priceTypeName": "Wholesale"}, {"adm0Code": 73, "commodityDateMonth": 1, "commodityDateWeek": null, "commodityDateYear": 2021, "commodityID": 83, "commodityName": "Potatoes", "commodityPrice": 0.0, "commodityPriceDate": "2021-01-15T00:00:00", "commodityPriceFlag": "forecast", "commodityPriceObservations": null, "commodityPriceSourceName": "", "commodityUnitID": 5, "commodityUnitName": "KG", "countryISO3": "ECU", "countryName": "Ecuador", "currencyID": 28, "currencyName": "USD", "marketID": 2563, "marketName": "Ambato", "originalFrequency": "monthly", "priceTypeID": 14, "priceTypeName": "Wholesale"}, {"adm0Code": 73, "commodityDateMonth": 4, "commodityDateWeek": null, "commodityDateYear": 2020, "commodityID": 599, "commodityName": "Wheat (imported)", "commodityPrice": 0.0, "commodityPriceDate": "2020-04-15T00:00:00", "commodityPriceFlag": "forecast", "commodityPriceObservations": null, "commodityPriceSourceName": "", "commodityUnitID": 93, "commodityUnitName": "100 Pounds", "countryISO3": "ECU", "countryName": "Ecuador", "currencyID": 28, "currencyName": "USD", "marketID": 2598, "marketName": "Quito", "originalFrequency": "monthly", "priceTypeID": 14, "priceTypeName": "Wholesale"}, {"adm0Code": 73, "commodityDateMonth": 6, "commodityDateWeek": null, "commodityDateYear": 2021, "commodityID": 136, "commodityName": "Maize (yellow)", "commodityPrice": 0.0, "commodityPriceDate": "2021-06-15T00:00:00", "commodityPriceFlag": "forecast", "commodityPriceObservations": null, "commodityPriceSourceName": "", "commodityUnitID": 93, "commodityUnitName": "100 Pounds", "countryISO3": "ECU", "countryName": "Ecuador", "currencyID": 28, "currencyName": "USD", "marketID": 2573, "marketName": "Cuenca", "originalFrequency": "monthly", "priceTypeID": 14, "priceTypeName": "Wholesale"}, {"adm0Code": 73, "commodityDateMonth": 3, "commodityDateWeek": null, "commodityDateYear": 2021, "commodityID": 51, "commodityName": "Maize", "commodityPrice": 0.0, "commodityPriceDate": "2021-03-15T00:00:00", "commodityPriceFlag": "forecast", "commodityPriceObservations": null, "commodityPriceSourceName": "", "commodityUnitID": 5, "commodityUnitName": "KG", "countryISO3": "ECU", "countryName": "Ecuador", "currencyID": 28, "currencyName": "USD", "marketID": 2563, "marketName": "Ambato", "originalFrequency": "monthly", "priceTypeID": 14, "priceTypeName": "Wholesale"}, {"adm0Code": 73, "commodityDateMonth": 7, "commodityDateWeek": null, "commodityDateYear": 2020, "commodityID": 136, "commodityName": "Maize (yellow)", "commodityPrice": 0.0, "commodityPriceDate": "2020-07-15T00:00:00", "commodityPriceFlag": "forecast", "commodityPriceObservations": null, "commodityPriceSourceName": "", "commodityUnitID": 93, "commodityUnitName": "100 Pounds", "countryISO3": "ECU", "countryName": "Ecuador", "currencyID": 28, "currencyName": "USD", "marketID": 2582, "marketName": "Guayaquil", "originalFrequency": "monthly", "priceTypeID": 14, "priceTypeName": "Wholesale"}, {"adm0Code": 73, "commodityDateMonth": 5, "commodityDateWeek": null, "commodityDateYear": 2021, "commodityID": 162, "commodityName": "Rice (long grain)", "commodityPrice": 0.0, "commodityPriceDate": "2021-05-15T00:00:00", "commodityPriceFlag": "forecast", "commodityPriceObservations": null, "commodityPriceSourceName": "", "commodityUnitID": 5, "commodityUnitName": "KG", "countryISO3": "ECU", "countryName": "Ecuador", "currencyID": 28, "currencyName": "USD", "marketID": 2582, "marketName": "Guayaquil", "originalFrequency": "monthly", "priceTypeID": 14, "priceTypeName": "Wholesale"}, {"adm0Code": 73, "commodityDateMonth": 7, "commodityDateWeek": null, "commodityDateYear": 2020, "commodityID": 136, "commodityName": "Maize (yellow)", "commodityPrice": 0.0, "commodityPriceDate": "2020-07-15T00:00:00", "commodityPriceFlag": "forecast", "commodityPriceObservations": null, "commodityPriceSourceName": "", "commodityUnitID": 93, "commodityUnitName": "100 Pounds", "countryISO3": "ECU", "countryName": "Ecuador", "currencyID": 28, "currencyName": "USD", "marketID": 2598, "marketName": "Quito", "originalFrequency": "monthly", "priceTypeID": 14, "priceTypeName": "Wholesale"}, {"adm0Code": 73, "commodityDateMonth": 5, "commodityDateWeek": null, "commodityDateYear": 2021, "commodityID": 136, "commodityName": "Maize (yellow)", "commodityPrice": 0.0, "commodityPriceDate": "2021-05-15T00:00:00", "commodityPriceFlag": "forecast", "commodityPriceObservations": null, "commodityPriceSourceName": "", "commodityUnitID": 93, "commodityUnitName": "100 Pounds", "countryISO3": "ECU", "countryName": "Ecuador", "currencyID": 28, "currencyName": "USD", "marketID": 2573, "marketName": "Cuenca", "originalFrequency": "monthly", "priceTypeID": 14, "priceTypeName": "Wholesale"}, {"adm0Code": 73, "commodityDateMonth": 4, "commodityDateWeek": null, "commodityDateYear": 2021, "commodityID": 51, "commodityName": "Maize", "commodityPrice": 0.0, "commodityPriceDate": "2021-04-15T00:00:00", "commodityPriceFlag": "forecast", "commodityPriceObservations": null, "commodityPriceSourceName": "", "commodityUnitID": 5, "commodityUnitName": "KG", "countryISO3": "ECU", "countryName": "Ecuador", "currencyID": 28, "currencyName": "USD", "marketID": 2563, "marketName": "Ambato", "originalFrequency": "monthly", "priceTypeID": 14, "priceTypeName": "Wholesale"}, {"adm0Code": 73, "commodityDateMonth": 8, "commodityDateWeek": null, "commodityDateYear": 2017, "commodityID": 162, "commodityName": "Rice (long grain)", "commodityPrice": 0.0, "commodityPriceDate": "2017-08-15T00:00:00", "commodityPriceFlag": "forecast", "commodityPriceObservations": null, "commodityPriceSourceName": "", "commodityUnitID": 5, "commodityUnitName": "KG", "countryISO3": "ECU", "countryName": "Ecuador", "currencyID": 28, "currencyName": "USD", "marketID": 2596, "marketName": "Portoviejo", "originalFrequency": "monthly", "priceTypeID": 14, "priceTypeName": "Wholesale"}, {"adm0Code": 73, "commodityDateMonth": 1, "commodityDateWeek": null, "commodityDateYear": 2021, "commodityID": 51, "commodityName": "Maize", "commodityPrice": 0.0, "commodityPriceDate": "2021-01-15T00:00:00", "commodityPriceFlag": "forecast", "commodityPriceObservations": null, "commodityPriceSourceName": "", "commodityUnitID": 5, "commodityUnitName": "KG", "countryISO3": "ECU", "countryName": "Ecuador", "currencyID": 28, "currencyName": "USD", "marketID": 2573, "marketName": "Cuenca", "originalFrequency": "monthly", "priceTypeID": 14, "priceTypeName": "Wholesale"}, {"adm0Code": 73, "commodityDateMonth": 1, "commodityDateWeek": null, "commodityDateYear": 2021, "commodityID": 51, "commodityName": "Maize", "commodityPrice": 0.0, "commodityPriceDate": "2021-01-15T00:00:00", "commodityPriceFlag": "forecast", "commodityPriceObservations": null, "commodityPriceSourceName": "", "commodityUnitID": 5, "commodityUnitName": "KG", "countryISO3": "ECU", "countryName": "Ecuador", "currencyID": 28, "currencyName": "USD", "marketID": 2563, "marketName": "Ambato", "originalFrequency": "monthly", "priceTypeID": 14, "priceTypeName": "Wholesale"}, {"adm0Code": 73, "commodityDateMonth": 9, "commodityDateWeek": null, "commodityDateYear": 2020, "commodityID": 58, "commodityName": "Wheat flour", "commodityPrice": 0.0, "commodityPriceDate": "2020-09-15T00:00:00", "commodityPriceFlag": "forecast", "commodityPriceObservations": null, "commodityPriceSourceName": "", "commodityUnitID": 22, "commodityUnitName": "50 KG", "countryISO3": "ECU", "countryName": "Ecuador", "currencyID": 28, "currencyName": "USD", "marketID": 2598, "marketName": "Quito", "originalFrequency": "monthly", "priceTypeID": 14, "priceTypeName": "Wholesale"}, {"adm0Code": 73, "commodityDateMonth": 5, "commodityDateWeek": null, "commodityDateYear": 2020, "commodityID": 83, "commodityName": "Potatoes", "commodityPrice": 0.0, "commodityPriceDate": "2020-05-15T00:00:00", "commodityPriceFlag": "forecast", "commodityPriceObservations": null, "commodityPriceSourceName": "", "commodityUnitID": 5, "commodityUnitName": "KG", "countryISO3": "ECU", "countryName": "Ecuador", "currencyID": 28, "currencyName": "USD", "marketID": 2598, "marketName": "Quito", "originalFrequency": "monthly", "priceTypeID": 14, "priceTypeName": "Wholesale"}, {"adm0Code": 73, "commodityDateMonth": 5, "commodityDateWeek": null, "commodityDateYear": 2021, "commodityID": 51, "commodityName": "Maize", "commodityPrice": 0.0, "commodityPriceDate": "2021-05-15T00:00:00", "commodityPriceFlag": "forecast", "commodityPriceObservations": null, "commodityPriceSourceName": "", "commodityUnitID": 5, "commodityUnitName": "KG", "countryISO3": "ECU", "countryName": "Ecuador", "currencyID": 28, "currencyName": "USD", "marketID": 2563, "marketName": "Ambato", "originalFrequency": "monthly", "priceTypeID": 14, "priceTypeName": "Wholesale"}, {"adm0Code": 73, "commodityDateMonth": 9, "commodityDateWeek": null, "commodityDateYear": 2017, "commodityID": 162, "commodityName": "Rice (long grain)", "commodityPrice": 0.0, "commodityPriceDate": "2017-09-15T00:00:00", "commodityPriceFlag": "forecast", "commodityPriceObservations": null, "commodityPriceSourceName": "", "commodityUnitID": 5, "commodityUnitName": "KG", "countryISO3": "ECU", "countryName": "Ecuador", "currencyID": 28, "currencyName": "USD", "marketID": 2563, "marketName": "Ambato", "originalFrequency": "monthly", "priceTypeID": 14, "priceTypeName": "Wholesale"}, {"adm0Code": 73, "commodityDateMonth": 11, "commodityDateWeek": null, "commodityDateYear": 2017, "commodityID": 162, "commodityName": "Rice (long grain)", "commodityPrice": 0.0, "commodityPriceDate": "2017-11-15T00:00:00", "commodityPriceFlag": "forecast", "commodityPriceObservations": null, "commodityPriceSourceName": "", "commodityUnitID": 5, "commodityUnitName": "KG", "countryISO3": "ECU", "countryName": "Ecuador", "currencyID": 28, "currencyName": "USD", "marketID": 2596, "marketName": "Portoviejo", "originalFrequency": "monthly", "priceTypeID": 14, "priceTypeName": "Wholesale"}, {"adm0Code": 73, "commodityDateMonth": 4, "commodityDateWeek": null, "commodityDateYear": 2020, "commodityID": 83, "commodityName": "Potatoes", "commodityPrice": 0.0, "commodityPriceDate": "2020-04-15T00:00:00", "commodityPriceFlag": "forecast", "commodityPriceObservations": null, "commodityPriceSourceName": "", "commodityUnitID": 5, "commodityUnitName": "KG", "countryISO3": "ECU", "countryName": "Ecuador", "currencyID": 28, "currencyName": "USD", "marketID": 2582, "marketName": "Guayaquil", "originalFrequency": "monthly", "priceTypeID": 14, "priceTypeName": "Wholesale"}, {"adm0Code": 73, "commodityDateMonth": 6, "commodityDateWeek": null, "commodityDateYear": 2021, "commodityID": 83, "commodityName": "Potatoes", "commodityPrice": 0.0, "commodityPriceDate": "2021-06-15T00:00:00", "commodityPriceFlag": "forecast", "commodityPriceObservations": null, "commodityPriceSourceName": "", "commodityUnitID": 5, "commodityUnitName": "KG", "countryISO3": "ECU", "countryName": "Ecuador", "currencyID": 28, "currencyName": "USD", "marketID": 2563, "marketName": "Ambato", "originalFrequency": "monthly", "priceTypeID": 14, "priceTypeName": "Wholesale"}, {"adm0Code": 73, "commodityDateMonth": 11, "commodityDateWeek": null, "commodityDateYear": 2017, "commodityID": 58, "commodityName": "Wheat flour", "commodityPrice": 0.0, "commodityPriceDate": "2017-11-15T00:00:00", "commodityPriceFlag": "forecast", "commodityPriceObservations": null, "commodityPriceSourceName": "", "commodityUnitID": 5, "commodityUnitName": "KG", "countryISO3": "ECU", "countryName": "Ecuador", "currencyID": 28, "currencyName": "USD", "marketID": 2596, "marketName": "Portoviejo", "originalFrequency": "monthly", "priceTypeID": 14, "priceTypeName": "Wholesale"}, {"adm0Code": 73, "commodityDateMonth": 10, "commodityDateWeek": null, "commodityDateYear": 2017, "commodityID": 162, "commodityName": "Rice (long grain)", "commodityPrice": 0.0, "commodityPriceDate": "2017-10-15T00:00:00", "commodityPriceFlag": "forecast", "commodityPriceObservations": null, "commodityPriceSourceName": "", "commodityUnitID": 5, "commodityUnitName": "KG", "countryISO3": "ECU", "countryName": "Ecuador", "currencyID": 28, "currencyName": "USD", "marketID": 2596, "marketName": "Portoviejo", "originalFrequency": "monthly", "priceTypeID": 14, "priceTypeName": "Wholesale"}, {"adm0Code": 73, "commodityDateMonth": 8, "commodityDateWeek": null, "commodityDateYear": 2020, "commodityID": 51, "commodityName": "Maize", "commodityPrice": 0.0, "commodityPriceDate": "2020-08-15T00:00:00", "commodityPriceFlag": "forecast", "commodityPriceObservations": null, "commodityPriceSourceName": "", "commodityUnitID": 5, "commodityUnitName": "KG", "countryISO3": "ECU", "countryName": "Ecuador", "currencyID": 28, "currencyName": "USD", "marketID": 2598, "marketName": "Quito", "originalFrequency": "monthly", "priceTypeID": 14, "priceTypeName": "Wholesale"}, {"adm0Code": 73, "commodityDateMonth": 7, "commodityDateWeek": null, "commodityDateYear": 2020, "commodityID": 599, "commodityName": "Wheat (imported)", "commodityPrice": 0.0, "commodityPriceDate": "2020-07-15T00:00:00", "commodityPriceFlag": "forecast", "commodityPriceObservations": null, "commodityPriceSourceName": "", "commodityUnitID": 93, "commodityUnitName": "100 Pounds", "countryISO3": "ECU", "countryName": "Ecuador", "currencyID": 28, "currencyName": "USD", "marketID": 2598, "marketName": "Quito", "originalFrequency": "monthly", "priceTypeID": 14, "priceTypeName": "Wholesale"}, {"adm0Code": 73, "commodityDateMonth": 1, "commodityDateWeek": null, "commodityDateYear": 2021, "commodityID": 51, "commodityName": "Maize", "commodityPrice": 0.0, "commodityPriceDate": "2021-01-15T00:00:00", "commodityPriceFlag": "forecast", "commodityPriceObservations": null, "commodityPriceSourceName": "", "commodityUnitID": 5, "commodityUnitName": "KG", "countryISO3": "ECU", "countryName": "Ecuador", "currencyID": 28, "currencyName": "USD", "marketID": 2599, "marketName": "Riobamba", "originalFrequency": "monthly", "priceTypeID": 14, "priceTypeName": "Wholesale"}, {"adm0Code": 73, "commodityDateMonth": 6, "commodityDateWeek": null, "commodityDateYear": 2021, "commodityID": 162, "commodityName": "Rice (long grain)", "commodityPrice": 0.0, "commodityPriceDate": "2021-06-15T00:00:00", "commodityPriceFlag": "forecast", "commodityPriceObservations": null, "commodityPriceSourceName": "", "commodityUnitID": 5, "commodityUnitName": "KG", "countryISO3": "ECU", "countryName": "Ecuador", "currencyID": 28, "currencyName": "USD", "marketID": 2598, "marketName": "Quito", "originalFrequency": "monthly", "priceTypeID": 14, "priceTypeName": "Wholesale"}, {"adm0Code": 73, "commodityDateMonth": 6, "commodityDateWeek": null, "commodityDateYear": 2020, "commodityID": 83, "commodityName": "Potatoes", "commodityPrice": 0.0, "commodityPriceDate": "2020-06-15T00:00:00", "commodityPriceFlag": "forecast", "commodityPriceObservations": null, "commodityPriceSourceName": "", "commodityUnitID": 5, "commodityUnitName": "KG", "countryISO3": "ECU", "countryName": "Ecuador", "currencyID": 28, "currencyName": "USD", "marketID": 2598, "marketName": "Quito", "originalFrequency": "monthly", "priceTypeID": 14, "priceTypeName": "Wholesale"}, {"adm0Code": 73, "commodityDateMonth": 4, "commodityDateWeek": null, "commodityDateYear": 2021, "commodityID": 162, "commodityName": "Rice (long grain)", "commodityPrice": 0.0, "commodityPriceDate": "2021-04-15T00:00:00", "commodityPriceFlag": "forecast", "commodityPriceObservations": null, "commodityPriceSourceName": "", "commodityUnitID": 5, "commodityUnitName": "KG", "countryISO3": "ECU", "countryName": "Ecuador", "currencyID": 28, "currencyName": "USD", "marketID": 2582, "marketName": "Guayaquil", "originalFrequency": "monthly", "priceTypeID": 14, "priceTypeName": "Wholesale"}, {"adm0Code": 73, "commodityDateMonth": 4, "commodityDateWeek": null, "commodityDateYear": 2021, "commodityID": 162, "commodityName": "Rice (long grain)", "commodityPrice": 0.0, "commodityPriceDate": "2021-04-15T00:00:00", "commodityPriceFlag": "forecast", "commodityPriceObservations": null, "commodityPriceSourceName": "", "commodityUnitID": 5, "commodityUnitName": "KG", "countryISO3": "ECU", "countryName": "Ecuador", "currencyID": 28, "currencyName": "USD", "marketID": 2598, "marketName": "Quito", "originalFrequency": "monthly", "priceTypeID": 14, "priceTypeName": "Wholesale"}, {"adm0Code": 73, "commodityDateMonth": 1, "commodityDateWeek": null, "commodityDateYear": 2021, "commodityID": 136, "commodityName": "Maize (yellow)", "commodityPrice": 0.0, "commodityPriceDate": "2021-01-15T00:00:00", "commodityPriceFlag": "forecast", "commodityPriceObservations": null, "commodityPriceSourceName": "", "commodityUnitID": 93, "commodityUnitName": "100 Pounds", "countryISO3": "ECU", "countryName": "Ecuador", "currencyID": 28, "currencyName": "USD", "marketID": 2596, "marketName": "Portoviejo", "originalFrequency": "monthly", "priceTypeID": 14, "priceTypeName": "Wholesale"}, {"adm0Code": 73, "commodityDateMonth": 2, "commodityDateWeek": null, "commodityDateYear": 2021, "commodityID": 51, "commodityName": "Maize", "commodityPrice": 0.0, "commodityPriceDate": "2021-02-15T00:00:00", "commodityPriceFlag": "forecast", "commodityPriceObservations": null, "commodityPriceSourceName": "", "commodityUnitID": 5, "commodityUnitName": "KG", "countryISO3": "ECU", "countryName": "Ecuador", "currencyID": 28, "currencyName": "USD", "marketID": 2573, "marketName": "Cuenca", "originalFrequency": "monthly", "priceTypeID": 14, "priceTypeName": "Wholesale"}, {"adm0Code": 73, "commodityDateMonth": 10, "commodityDateWeek": null, "commodityDateYear": 2017, "commodityID": 162, "commodityName": "Rice (long grain)", "commodityPrice": 0.0, "commodityPriceDate": "2017-10-15T00:00:00", "commodityPriceFlag": "forecast", "commodityPriceObservations": null, "commodityPriceSourceName": "", "commodityUnitID": 5, "commodityUnitName": "KG", "countryISO3": "ECU", "countryName": "Ecuador", "currencyID": 28, "currencyName": "USD", "marketID": 2563, "marketName": "Ambato", "originalFrequency": "monthly", "priceTypeID": 14, "priceTypeName": "Wholesale"}, {"adm0Code": 73, "commodityDateMonth": 7, "commodityDateWeek": null, "commodityDateYear": 2021, "commodityID": 162, "commodityName": "Rice (long grain)", "commodityPrice": 0.0, "commodityPriceDate": "2021-07-15T00:00:00", "commodityPriceFlag": "forecast", "commodityPriceObservations": null, "commodityPriceSourceName": "", "commodityUnitID": 5, "commodityUnitName": "KG", "countryISO3": "ECU", "countryName": "Ecuador", "currencyID": 28, "currencyName": "USD", "marketID": 2598, "marketName": "Quito", "originalFrequency": "monthly", "priceTypeID": 14, "priceTypeName": "Wholesale"}, {"adm0Code": 73, "commodityDateMonth": 8, "commodityDateWeek": null, "commodityDateYear": 2020, "commodityID": 58, "commodityName": "Wheat flour", "commodityPrice": 0.0, "commodityPriceDate": "2020-08-15T00:00:00", "commodityPriceFlag": "forecast", "commodityPriceObservations": null, "commodityPriceSourceName": "", "commodityUnitID": 22, "commodityUnitName": "50 KG", "countryISO3": "ECU", "countryName": "Ecuador", "currencyID": 28, "currencyName": "USD", "marketID": 2598, "marketName": "Quito", "originalFrequency": "monthly", "priceTypeID": 14, "priceTypeName": "Wholesale"}, {"adm0Code": 73, "commodityDateMonth": 6, "commodityDateWeek": null, "commodityDateYear": 2021, "commodityID": 162, "commodityName": "Rice (long grain)", "commodityPrice": 0.0, "commodityPriceDate": "2021-06-15T00:00:00", "commodityPriceFlag": "forecast", "commodityPriceObservations": null, "commodityPriceSourceName": "", "commodityUnitID": 5, "commodityUnitName": "KG", "countryISO3": "ECU", "countryName": "Ecuador", "currencyID": 28, "currencyName": "USD", "marketID": 2582, "marketName": "Guayaquil", "originalFrequency": "monthly", "priceTypeID": 14, "priceTypeName": "Wholesale"}, {"adm0Code": 73, "commodityDateMonth": 3, "commodityDateWeek": null, "commodityDateYear": 2021, "commodityID": 51, "commodityName": "Maize", "commodityPrice": 0.0, "commodityPriceDate": "2021-03-15T00:00:00", "commodityPriceFlag": "forecast", "commodityPriceObservations": null, "commodityPriceSourceName": "", "commodityUnitID": 5, "commodityUnitName": "KG", "countryISO3": "ECU", "countryName": "Ecuador", "currencyID": 28, "currencyName": "USD", "marketID": 2599, "marketName": "Riobamba", "originalFrequency": "monthly", "priceTypeID": 14, "priceTypeName": "Wholesale"}, {"adm0Code": 73, "commodityDateMonth": 6, "commodityDateWeek": null, "commodityDateYear": 2020, "commodityID": 51, "commodityName": "Maize", "commodityPrice": 0.0, "commodityPriceDate": "2020-06-15T00:00:00", "commodityPriceFlag": "forecast", "commodityPriceObservations": null, "commodityPriceSourceName": "", "commodityUnitID": 5, "commodityUnitName": "KG", "countryISO3": "ECU", "countryName": "Ecuador", "currencyID": 28, "currencyName": "USD", "marketID": 2582, "marketName": "Guayaquil", "originalFrequency": "monthly", "priceTypeID": 14, "priceTypeName": "Wholesale"}, {"adm0Code": 73, "commodityDateMonth": 6, "commodityDateWeek": null, "commodityDateYear": 2017, "commodityID": 162, "commodityName": "Rice (long grain)", "commodityPrice": 0.0, "commodityPriceDate": "2017-06-15T00:00:00", "commodityPriceFlag": "forecast", "commodityPriceObservations": null, "commodityPriceSourceName": "", "commodityUnitID": 5, "commodityUnitName": "KG", "countryISO3": "ECU", "countryName": "Ecuador", "currencyID": 28, "currencyName": "USD", "marketID": 2563, "marketName": "Ambato", "originalFrequency": "monthly", "priceTypeID": 14, "priceTypeName": "Wholesale"}, {"adm0Code": 73, "commodityDateMonth": 4, "commodityDateWeek": null, "commodityDateYear": 2021, "commodityID": 136, "commodityName": "Maize (yellow)", "commodityPrice": 0.0, "commodityPriceDate": "2021-04-15T00:00:00", "commodityPriceFlag": "forecast", "commodityPriceObservations": null, "commodityPriceSourceName": "", "commodityUnitID": 93, "commodityUnitName": "100 Pounds", "countryISO3": "ECU", "countryName": "Ecuador", "currencyID": 28, "currencyName": "USD", "marketID": 2573, "marketName": "Cuenca", "originalFrequency": "monthly", "priceTypeID": 14, "priceTypeName": "Wholesale"}, {"adm0Code": 73, "commodityDateMonth": 1, "commodityDateWeek": null, "commodityDateYear": 2021, "commodityID": 162, "commodityName": "Rice (long grain)", "commodityPrice": 0.0, "commodityPriceDate": "2021-01-15T00:00:00", "commodityPriceFlag": "forecast", "commodityPriceObservations": null, "commodityPriceSourceName": "", "commodityUnitID": 5, "commodityUnitName": "KG", "countryISO3": "ECU", "countryName": "Ecuador", "currencyID": 28, "currencyName": "USD", "marketID": 2573, "marketName": "Cuenca", "originalFrequency": "monthly", "priceTypeID": 14, "priceTypeName": "Wholesale"}, {"adm0Code": 73, "commodityDateMonth": 2, "commodityDateWeek": null, "commodityDateYear": 2021, "commodityID": 136, "commodityName": "Maize (yellow)", "commodityPrice": 0.0, "commodityPriceDate": "2021-02-15T00:00:00", "commodityPriceFlag": "forecast", "commodityPriceObservations": null, "commodityPriceSourceName": "", "commodityUnitID": 93, "commodityUnitName": "100 Pounds", "countryISO3": "ECU", "countryName": "Ecuador", "currencyID": 28, "currencyName": "USD", "marketID": 2573, "marketName": "Cuenca", "originalFrequency": "monthly", "priceTypeID": 14, "priceTypeName": "Wholesale"}, {"adm0Code": 73, "commodityDateMonth": 6, "commodityDateWeek": null, "commodityDateYear": 2020, "commodityID": 136, "commodityName": "Maize (yellow)", "commodityPrice": 0.0, "commodityPriceDate": "2020-06-15T00:00:00", "commodityPriceFlag": "forecast", "commodityPriceObservations": null, "commodityPriceSourceName": "", "commodityUnitID": 93, "commodityUnitName": "100 Pounds", "countryISO3": "ECU", "countryName": "Ecuador", "currencyID": 28, "currencyName": "USD", "marketID": 2582, "marketName": "Guayaquil", "originalFrequency": "monthly", "priceTypeID": 14, "priceTypeName": "Wholesale"}], "page": 5, "totalItems": 4077}